mkdocstrings_handlers/python_accessors/__init__.py
mkdocstrings_handlers/python_accessors/handler.py
mkdocstrings_handlers/python_accessors/py.typed
mkdocstrings_python_accessors-0.1.2.dist-info/METADATA
mkdocstrings_python_accessors-0.1.2.dist-info/WHEEL
mkdocstrings_python_accessors-0.1.2.dist-info/entry_points.txt
mkdocstrings_python_accessors-0.1.2.dist-info/licenses/LICENCE
mkdocstrings_python_accessors-0.1.2.dist-info/RECORD
