Metadata-Version: 2.1
Name: mkdocstrings-python-accessors
Version: 0.1.2
Summary: Support for documenting accessors with mkdocstrings.
Author-Email: Zebedee Nicholls <zebedee.nicholls@climate-resource.com>
License: BSD-3-Clause
Classifier: License :: OSI Approved :: BSD License
Classifier: Development Status :: 4 - Beta
Classifier: Intended Audience :: Developers
Classifier: Programming Language :: Python
Classifier: Programming Language :: Python :: 3
Classifier: Programming Language :: Python :: 3 :: Only
Classifier: Programming Language :: Python :: 3.9
Classifier: Programming Language :: Python :: 3.10
Classifier: Programming Language :: Python :: 3.11
Classifier: Programming Language :: Python :: 3.12
Classifier: Programming Language :: Python :: 3.13
Classifier: Topic :: Documentation
Classifier: Topic :: Software Development
Classifier: Topic :: Utilities
Classifier: Typing :: Typed
Project-URL: Homepage, https://github.com/climate-resource/mkdocstrings-python-accessors
Project-URL: Documentation, https://github.com/climate-resource/mkdocstrings-python-accessors
Project-URL: Changelog, https://github.com/climate-resource/mkdocstrings-python-accessors/blob/main/docs/changelog.md
Project-URL: Repository, https://github.com/climate-resource/mkdocstrings-python-accessors
Project-URL: Issues, https://github.com/climate-resource/mkdocstrings-python-accessors/issues
Requires-Python: >=3.9
Requires-Dist: mkdocstrings-python-xref>=1.0
